{"cameraMode":{"drawMode":0,"name":"Shaded","section":"Shading Mode"},"sceneLighting":true,"audioPlay":false,"sceneViewState":{"showFog":true,"showMaterialUpdate":false,"showSkybox":true,"showFlares":true,"showImageEffects":true,"showParticleSystems":true},"in2DMode":false,"pivot":{"x":-0.7246299982070923,"y":-2.901742458343506,"z":0.02285417728126049},"rotation":{"x":-0.4318910539150238,"y":-0.5536820292472839,"z":0.41164731979370119,"w":-0.5809117555618286},"size":29.596576690673829,"orthographic":false}